radarplt/__init__.py
radarplt/factory.py
radarplt/helpers.py
radarplt-2.2.2.dist-info/LICENSE
radarplt-2.2.2.dist-info/METADATA
radarplt-2.2.2.dist-info/WHEEL
radarplt-2.2.2.dist-info/RECORD
