Metadata-Version: 2.1
Name: radarplt
Version: 2.2.2
Summary: 
Home-page: https://github.com/jdkern11/radar_plot.git
Author: jdkern11
Author-email: josephdanielkern@gmail.com
Requires-Python: >=3.9,<3.13
Classifier: Programming Language :: Python :: 3
Classifier: Programming Language :: Python :: 3.9
Classifier: Programming Language :: Python :: 3.10
Classifier: Programming Language :: Python :: 3.11
Requires-Dist: matplotlib (>=3.6.3,<4.0.0)
Requires-Dist: pandas (>=1.4.4)
Project-URL: Repository, https://github.com/jdkern11/radar_plot.git
